{
  "aggregate": {
    "timestamp": "2020-06-28T22:40:14.717Z",
    "scenariosCreated": 967,
    "scenariosCompleted": 967,
    "requestsCompleted": 1934,
    "latency": {
      "min": 59.9,
      "max": 10154.4,
      "median": 484.7,
      "p95": 7387.6,
      "p99": 8827.3
    },
    "rps": {
      "count": 1934,
      "mean": 8.34
    },
    "scenarioDuration": {
      "min": 30185.4,
      "max": 40601.5,
      "median": 31403.6,
      "p95": 39274.2,
      "p99": 39886.1
    },
    "scenarioCounts": {
      "Ride": 967
    },
    "errors": {},
    "codes": {
      "200": 1934
    },
    "matches": 0,
    "customStats": {},
    "counters": {},
    "scenariosAvoided": 0,
    "phases": [
      {
        "duration": 5,
        "arrivalRate": 5,
        "rampTo": 25
      },
      {
        "duration": 10,
        "arrivalRate": 5
      },
      {
        "duration": 10,
        "arrivalRate": 20
      },
      {
        "pause": 60
      },
      {
        "duration": 10,
        "arrivalRate": 10,
        "rampTo": 60
      },
      {
        "pause": 30
      },
      {
        "duration": 5,
        "arrivalRate": 10,
        "rampTo": 30
      },
      {
        "pause": 30
      },
      {
        "duration": 5,
        "arrivalRate": 10
      },
      {
        "duration": 5,
        "arrivalRate": 20
      },
      {
        "duration": 30,
        "arrivalRate": 1
      }
    ]
  },
  "intermediate": [
    {
      "timestamp": "2020-06-28T22:36:32.667Z",
      "scenariosCreated": 93,
      "scenariosCompleted": 0,
      "requestsCompleted": 17,
      "latency": {
        "min": 3635.3,
        "max": 7207.4,
        "median": 6406.4,
        "p95": 7206.4,
        "p99": 7207.4
      },
      "rps": {
        "count": 93,
        "mean": 9.39
      },
      "scenarioDuration": {
        "min": null,
        "max": null,
        "median": null,
        "p95": null,
        "p99": null
      },
      "scenarioCounts": {
        "Ride": 93
      },
      "errors": {},
      "codes": {
        "200": 17
      },
      "matches": 0,
      "latencies": [
        3635288674,
        3657257283,
        4808140103,
        5095474050,
        5055392872,
        4856877487,
        4618907948,
        6727053297,
        6612250663,
        6406442429,
        6488006213,
        5440356415,
        7124431978,
        7207362259,
        7120655466,
        7204578009,
        7163623157
      ],
      "customStats": {},
      "counters": {},
      "concurrency": 93,
      "pendingRequests": 76,
      "scenariosAvoided": 0
    },
    {
      "timestamp": "2020-06-28T22:36:42.662Z",
      "scenariosCreated": 125,
      "scenariosCompleted": 0,
      "requestsCompleted": 104,
      "latency": {
        "min": 3244.4,
        "max": 10154.4,
        "median": 8164.5,
        "p95": 9460.4,
        "p99": 10007.1
      },
      "rps": {
        "count": 125,
        "mean": 12.55
      },
      "scenarioDuration": {
        "min": null,
        "max": null,
        "median": null,
        "p95": null,
        "p99": null
      },
      "scenarioCounts": {
        "Ride": 125
      },
      "errors": {},
      "codes": {
        "200": 104
      },
      "matches": 0,
      "latencies": [
        8327870272,
        8308775881,
        8478644111,
        8320638581,
        8279183044,
        8480145741,
        6441679896,
        8524595247,
        8403468490,
        8205534662,
        8249048661,
        8128731751,
        8049057819,
        7970266556,
        8411248668,
        8947581873,
        9347005055,
        9226476589,
        9180301657,
        9064231312,
        9528594303,
        7135500100,
        9009085324,
        9433729406,
        10154431258,
        8804364867,
        8763461402,
        9033738989,
        8603719616,
        6206709148,
        8685239312,
        9127874469,
        8666098553,
        9108023225,
        8548770299,
        8771163341,
        9132039891,
        9012202195,
        9254181435,
        8455230061,
        8574687844,
        8656257341,
        8615904072,
        8405225177,
        8364616831,
        8447102116,
        8725937586,
        8327180161,
        8766812616,
        8293152178,
        5404013181,
        5217451613,
        8527912389,
        9570092725,
        4847593237,
        8511192971,
        8994126060,
        9522486263,
        8404668000,
        9881564464,
        8200353239,
        8005264170,
        7826155967,
        7609683165,
        7741310677,
        7541942731,
        7351956821,
        7630298435,
        7466428620,
        7067001140,
        6667324852,
        6472535714,
        6072331808,
        5980565915,
        5781129121,
        5455985308,
        5837425996,
        5238773373,
        5039309791,
        5438871066,
        3244438702,
        4897319959,
        5102303443,
        4708758892,
        4310673534,
        4513580119,
        4476049043,
        4799513263,
        4474674254,
        4955055788,
        5556124786,
        4756054726,
        4157199562,
        4558560512,
        4358770329,
        4201126500,
        3924913968,
        4926471184,
        4730187113,
        3527938120,
        3629748022,
        4654456162,
        4455961485,
        4260561238
      ],
      "customStats": {},
      "counters": {},
      "concurrency": 218,
      "pendingRequests": 97,
      "scenariosAvoided": 0
    },
    {
      "timestamp": "2020-06-28T22:36:52.665Z",
      "scenariosCreated": 101,
      "scenariosCompleted": 0,
      "requestsCompleted": 198,
      "latency": {
        "min": 1654.6,
        "max": 8769.4,
        "median": 5256.7,
        "p95": 8218.6,
        "p99": 8696.1
      },
      "rps": {
        "count": 101,
        "mean": 10.14
      },
      "scenarioDuration": {
        "min": null,
        "max": null,
        "median": null,
        "p95": null,
        "p99": null
      },
      "scenarioCounts": {
        "Ride": 101
      },
      "errors": {},
      "codes": {
        "200": 198
      },
      "matches": 0,
      "latencies": [
        3770991265,
        5266573342,
        5418432938,
        5218300073,
        5363365116,
        5414704673,
        5165532123,
        5215637074,
        5150518667,
        5063788056,
        5121688491,
        5306714037,
        5108850436,
        4960412607,
        5160869218,
        5060829535,
        4909893751,
        4897091799,
        5050208606,
        5658078947,
        5807957879,
        5699919832,
        5947320908,
        4996562862,
        4846110976,
        5898983353,
        6238856160,
        5244702332,
        5246859260,
        6650656950,
        6557282668,
        5495064190,
        5145302230,
        5289695079,
        6544778186,
        5288441765,
        6689533471,
        5241715814,
        6597754913,
        6549611057,
        5207023255,
        6462055248,
        6563487739,
        6413667218,
        6512699413,
        6400805362,
        6659796911,
        3375735344,
        3229800982,
        6756599818,
        6820250427,
        5757165404,
        5777942029,
        5828537201,
        5730023036,
        7008204789,
        4377394133,
        5948615292,
        4304935529,
        4457569211,
        4255373519,
        4456063523,
        7955684746,
        6214315485,
        5967503692,
        3651561169,
        1654554765,
        7899978160,
        4219875789,
        4271110648,
        6043229502,
        6200507132,
        5903648513,
        8038009576,
        5942302901,
        8093832231,
        5897255634,
        5958015108,
        7957624453,
        4534802919,
        4637319730,
        8104880989,
        8612405504,
        8280506907,
        2403478065,
        4454505250,
        8213638699,
        4472455498,
        4973599281,
        5154487825,
        5204986067,
        6606151782,
        4807313559,
        6206543691,
        4607708882,
        3357729746,
        2658212657,
        4408332223,
        6060599988,
        6013269067,
        5914460314,
        8717089799,
        8617999437,
        5967281382,
        8769416967,
        8571533669,
        2572655790,
        8221903664,
        8673393030,
        5623016056,
        8473041320,
        8531991818,
        8182327464,
        5434105394,
        5534795009,
        8134469646,
        8090536854,
        8111099628,
        7914340731,
        5149925748,
        8048280763,
        8149382823,
        5300917975,
        7850409886,
        7701708161,
        4962466096,
        5413176245,
        7483661580,
        7536464234,
        7788146703,
        4888251117,
        7389083771,
        4789506003,
        7840227972,
        7339792613,
        4701933593,
        5202307923,
        4803140515,
        7354418672,
        5004931760,
        2754578254,
        4801358201,
        7381545328,
        2357798367,
        2661147772,
        2963417696,
        4667249645,
        7394124920,
        7347591541,
        7303982852,
        4361006375,
        3524894931,
        4540625168,
        7142646823,
        7199009361,
        4303330069,
        4104499505,
        7352608610,
        6504399848,
        4304411560,
        3017343420,
        3221271648,
        3824790835,
        3925851499,
        4259063776,
        6662590970,
        3163745770,
        4014938907,
        6415147852,
        3914710772,
        3815826874,
        3616928517,
        3368012684,
        3067596525,
        5717127202,
        3568980212,
        6118467074,
        5919003861,
        5219876157,
        4920467517,
        5169991523,
        5070498972,
        4719201288,
        5022301757,
        4972139799,
        2872821395,
        4674536025,
        3024887424,
        4474353654,
        3225855275,
        2925832328,
        4252103588,
        4897589809,
        3851378267,
        4602184646,
        3755262208,
        4080429319,
        3186336985
      ],
      "customStats": {},
      "counters": {},
      "concurrency": 319,
      "pendingRequests": 0,
      "scenariosAvoided": 0
    },
    {
      "timestamp": "2020-06-28T22:37:02.667Z",
      "scenariosCreated": 0,
      "scenariosCompleted": 17,
      "requestsCompleted": 17,
      "latency": {
        "min": 73.8,
        "max": 1119.7,
        "median": 327.1,
        "p95": 861.2,
        "p99": 1119.7
      },
      "rps": {
        "count": 17,
        "mean": 2.73
      },
      "scenarioDuration": {
        "min": 33786.8,
        "max": 37565.5,
        "median": 36740.9,
        "p95": 37560.8,
        "p99": 37565.5
      },
      "scenarioCounts": {},
      "errors": {},
      "codes": {
        "200": 17
      },
      "matches": 0,
      "latencies": [
        126661532,
        127135214,
        76356998,
        74894658,
        73788357,
        75638708,
        1119714349,
        357261139,
        323652716,
        381031772,
        347283011,
        242568006,
        327110559,
        327797444,
        348986565,
        349724823,
        349798525
      ],
      "customStats": {},
      "counters": {},
      "concurrency": 302,
      "pendingRequests": 0,
      "scenariosAvoided": 0
    },
    {
      "timestamp": "2020-06-28T22:37:12.672Z",
      "scenariosCreated": 0,
      "scenariosCompleted": 104,
      "requestsCompleted": 104,
      "latency": {
        "min": 67.5,
        "max": 1122.9,
        "median": 371.2,
        "p95": 864.6,
        "p99": 1095.8
      },
      "rps": {
        "count": 104,
        "mean": 10.97
      },
      "scenarioDuration": {
        "min": 33455.5,
        "max": 40601.5,
        "median": 38693,
        "p95": 39889.4,
        "p99": 40459.8
      },
      "scenarioCounts": {},
      "errors": {},
      "codes": {
        "200": 104
      },
      "matches": 0,
      "latencies": [
        651482843,
        629622333,
        423825590,
        424245722,
        372287719,
        372499088,
        342681919,
        342813350,
        558327046,
        307671538,
        907215625,
        901913972,
        292141309,
        918664638,
        309146059,
        1072774463,
        1122904176,
        303665823,
        303766862,
        387538638,
        438133939,
        438160385,
        457141112,
        484602319,
        388896422,
        721664774,
        794934507,
        795110409,
        620782072,
        766970288,
        723586236,
        361935565,
        768046965,
        738996161,
        489072483,
        757354482,
        757930257,
        490749587,
        490836868,
        465497685,
        465919990,
        462927252,
        417261005,
        497441501,
        718907816,
        313451191,
        746400197,
        749617910,
        747548033,
        717620128,
        523332651,
        721909437,
        500184941,
        728612175,
        848613255,
        663996529,
        663941740,
        371104312,
        371594895,
        369272456,
        372394555,
        371284857,
        351797284,
        244923672,
        79386588,
        224788341,
        219602465,
        67545111,
        101001192,
        104305945,
        352332118,
        356636818,
        356460453,
        249182498,
        249635100,
        262284812,
        203780335,
        203534736,
        204242990,
        207512507,
        256320370,
        120573795,
        115602840,
        191822277,
        271564144,
        271317967,
        397906441,
        69826638,
        162376171,
        108683417,
        103611206,
        104201517,
        191730704,
        196808424,
        242668068,
        118936908,
        146680403,
        254808684,
        164209373,
        265950729,
        164469629,
        134824975,
        135234268,
        135067039
      ],
      "customStats": {},
      "counters": {},
      "concurrency": 198,
      "pendingRequests": 0,
      "scenariosAvoided": 0
    },
    {
      "timestamp": "2020-06-28T22:37:22.675Z",
      "scenariosCreated": 0,
      "scenariosCompleted": 187,
      "requestsCompleted": 187,
      "latency": {
        "min": 68.2,
        "max": 2202.1,
        "median": 419.7,
        "p95": 2051.9,
        "p99": 2168.3
      },
      "rps": {
        "count": 198,
        "mean": 20.33
      },
      "scenarioDuration": {
        "min": 32070.2,
        "max": 40470.9,
        "median": 36410.6,
        "p95": 39670.1,
        "p99": 40210.2
      },
      "scenarioCounts": {},
      "errors": {},
      "codes": {
        "200": 187
      },
      "matches": 0,
      "latencies": [
        91394699,
        85056915,
        87493026,
        91462150,
        128696784,
        135051921,
        349746549,
        350173979,
        265389899,
        262295457,
        110763639,
        114287789,
        177304119,
        178597899,
        176222836,
        323327158,
        179245916,
        158753880,
        163463642,
        106397277,
        191902174,
        107818330,
        171811999,
        87158886,
        118252513,
        120660113,
        74510136,
        129043405,
        240752190,
        259251573,
        97245336,
        125261809,
        165462123,
        68220940,
        80311999,
        177635762,
        175180875,
        167769207,
        160238328,
        175341673,
        208850494,
        210605955,
        229458900,
        88942834,
        90897229,
        469760942,
        140353719,
        573180285,
        524945353,
        350046865,
        367751503,
        169771793,
        201741586,
        350370769,
        327409466,
        70588964,
        346421662,
        81034543,
        285528857,
        183500471,
        184917185,
        371595490,
        221463284,
        406171702,
        323085926,
        359973136,
        406711025,
        347168239,
        446711643,
        429253872,
        268553440,
        170381247,
        267731362,
        188792491,
        189010014,
        392707214,
        189762011,
        137501156,
        144069840,
        132530083,
        135154098,
        305722611,
        310998129,
        237930302,
        167240809,
        165429294,
        69903718,
        100427174,
        231853482,
        113546122,
        418950522,
        419667351,
        419284073,
        412243762,
        412010816,
        411653532,
        412236923,
        412210363,
        421374869,
        420901235,
        413425152,
        879045885,
        885202161,
        890249477,
        891853158,
        1005565568,
        1012315401,
        1033860180,
        1026109622,
        1015874358,
        1030366975,
        1090514628,
        1790609817,
        1785244597,
        1788869955,
        1790913875,
        1791651740,
        1527275099,
        1527771047,
        1545549034,
        1556318157,
        1520079031,
        1558717246,
        1565564899,
        1521508391,
        1748206032,
        1749107003,
        1671826602,
        1685085468,
        1751182178,
        1827145372,
        1848071747,
        1820645535,
        1752353409,
        1816961409,
        1752746234,
        2049940009,
        2160610080,
        2053748424,
        2064668547,
        2010205374,
        1950126229,
        2119699881,
        1980553414,
        1921392115,
        1950414110,
        1915355049,
        1924201606,
        1949416313,
        1951230946,
        2044657195,
        1974252848,
        2047352807,
        2051747776,
        1986578681,
        2068064769,
        1990703843,
        1970942906,
        2052812438,
        1977488965,
        1998667719,
        1739338586,
        1723235409,
        1979097688,
        1895513566,
        1895667057,
        2172817363,
        1914725611,
        1932659305,
        2202077309,
        1922172132,
        1923459385,
        1923610203,
        1923411192,
        1941388719,
        1924545788,
        1924507818,
        1924745185,
        1934153850,
        1939262299,
        2014324887,
        2032820113,
        2034564204,
        2035313000,
        2022999954,
        2089729047,
        2025273805
      ],
      "customStats": {},
      "counters": {},
      "concurrency": 11,
      "pendingRequests": 11,
      "scenariosAvoided": 0
    },
    {
      "timestamp": "2020-06-28T22:37:32.673Z",
      "scenariosCreated": 0,
      "scenariosCompleted": 11,
      "requestsCompleted": 11,
      "latency": {
        "min": 2013.4,
        "max": 2223,
        "median": 2174.7,
        "p95": 2222.7,
        "p99": 2223
      },
      "rps": {
        "count": 0,
        "mean": null
      },
      "scenarioDuration": {
        "min": 35122,
        "max": 37265.8,
        "median": 36216.1,
        "p95": 37251.4,
        "p99": 37265.8
      },
      "scenarioCounts": {},
      "errors": {},
      "codes": {
        "200": 11
      },
      "matches": 0,
      "latencies": [
        2068246894,
        2174451802,
        2174670890,
        2199597110,
        2208973774,
        2013418607,
        2146311289,
        2207228116,
        2222972719,
        2129957372,
        2218509247
      ],
      "customStats": {},
      "counters": {},
      "concurrency": 0,
      "pendingRequests": 0,
      "scenariosAvoided": 0
    },
    {
      "timestamp": "2020-06-28T22:37:42.675Z",
      "scenariosCreated": 0,
      "scenariosCompleted": 0,
      "requestsCompleted": 0,
      "latency": {
        "min": null,
        "max": null,
        "median": null,
        "p95": null,
        "p99": null
      },
      "rps": {
        "count": 0,
        "mean": null
      },
      "scenarioDuration": {
        "min": null,
        "max": null,
        "median": null,
        "p95": null,
        "p99": null
      },
      "scenarioCounts": {},
      "errors": {},
      "codes": {},
      "matches": 0,
      "latencies": [],
      "customStats": {},
      "counters": {},
      "concurrency": 0,
      "pendingRequests": 0,
      "scenariosAvoided": 0
    },
    {
      "timestamp": "2020-06-28T22:37:52.676Z",
      "scenariosCreated": 107,
      "scenariosCompleted": 0,
      "requestsCompleted": 90,
      "latency": {
        "min": 105.6,
        "max": 1149.5,
        "median": 415.7,
        "p95": 856,
        "p99": 1063.1
      },
      "rps": {
        "count": 107,
        "mean": 21.66
      },
      "scenarioDuration": {
        "min": null,
        "max": null,
        "median": null,
        "p95": null,
        "p99": null
      },
      "scenarioCounts": {
        "Ride": 107
      },
      "errors": {},
      "codes": {
        "200": 90
      },
      "matches": 0,
      "latencies": [
        121593070,
        132506599,
        264259405,
        366746834,
        387403137,
        428079002,
        510832265,
        480359280,
        471154376,
        501527499,
        338349113,
        232313945,
        419149692,
        144986253,
        105553609,
        298085296,
        511141342,
        483680532,
        402076980,
        220416893,
        443910454,
        568091780,
        302680467,
        380799856,
        168036057,
        445280101,
        604825583,
        224335711,
        276497589,
        145031141,
        199635079,
        134728439,
        205433763,
        120467458,
        191021117,
        331371142,
        416597149,
        283390015,
        250533354,
        431625299,
        928271133,
        666604091,
        901052145,
        855998164,
        687120789,
        660190834,
        765541951,
        933422542,
        1149501262,
        680925100,
        713419701,
        749918555,
        641820134,
        611031621,
        528364102,
        414893902,
        563061747,
        506033973,
        431251097,
        531747895,
        417165426,
        660302639,
        708123385,
        560693331,
        593960832,
        344004772,
        446293442,
        319875974,
        510110683,
        177245665,
        475813298,
        186176631,
        355272040,
        342783098,
        606499795,
        341075114,
        316657912,
        558208452,
        261233632,
        270577648,
        148871753,
        355496716,
        173948141,
        380293558,
        365437816,
        500710293,
        398738753,
        417109453,
        297864909,
        266628232
      ],
      "customStats": {},
      "counters": {},
      "concurrency": 107,
      "pendingRequests": 17,
      "scenariosAvoided": 0
    },
    {
      "timestamp": "2020-06-28T22:38:02.682Z",
      "scenariosCreated": 252,
      "scenariosCompleted": 0,
      "requestsCompleted": 239,
      "latency": {
        "min": 290.6,
        "max": 6041.9,
        "median": 965.9,
        "p95": 4915.5,
        "p99": 5615.3
      },
      "rps": {
        "count": 252,
        "mean": 25.35
      },
      "scenarioDuration": {
        "min": null,
        "max": null,
        "median": null,
        "p95": null,
        "p99": null
      },
      "scenarioCounts": {
        "Ride": 252
      },
      "errors": {},
      "codes": {
        "200": 239
      },
      "matches": 0,
      "latencies": [
        628899866,
        559150883,
        666788901,
        652969109,
        471479819,
        575208881,
        846200896,
        1212809775,
        1031072695,
        1078883750,
        1264786553,
        866348339,
        966100219,
        1048804294,
        619860309,
        954618736,
        654722106,
        822749799,
        573593850,
        472787235,
        391567233,
        441405835,
        462164031,
        933879831,
        739528895,
        523612791,
        498982471,
        550078061,
        800625046,
        648605937,
        851788664,
        454790583,
        474685724,
        463656254,
        355168227,
        523660648,
        539977442,
        623432700,
        531636462,
        372496646,
        665976113,
        572428528,
        520747398,
        445778255,
        628287232,
        581162254,
        385011935,
        357369515,
        451816476,
        594471870,
        662089958,
        478324983,
        626462377,
        828932129,
        493538921,
        597016872,
        613722476,
        643656103,
        748281916,
        363315085,
        815276666,
        478553317,
        512647044,
        416577619,
        397205286,
        429823442,
        299795141,
        465887005,
        548952013,
        431063617,
        667375215,
        380083850,
        420120557,
        318508553,
        1121482451,
        384735906,
        724718506,
        798617488,
        652591857,
        537635564,
        438992914,
        689352233,
        619191486,
        886251342,
        919981856,
        838559069,
        907337963,
        811672470,
        794932710,
        709617619,
        428711002,
        561476167,
        400001236,
        417491210,
        350001800,
        366282563,
        402087247,
        454949236,
        563052738,
        314082845,
        994414919,
        911440549,
        477532886,
        540111930,
        1142681491,
        637669059,
        1587871904,
        1252288561,
        1219039387,
        1601299263,
        1617786776,
        918078224,
        2168852152,
        837736938,
        1143190782,
        1183734470,
        965894894,
        1285371835,
        1051861162,
        1654330143,
        1042309127,
        1609680043,
        941167961,
        1228008219,
        781830719,
        900369090,
        1001098144,
        938571111,
        571175887,
        920692952,
        959189151,
        793211939,
        746036017,
        911986997,
        781149338,
        731045625,
        1263252948,
        802258140,
        672217111,
        857437113,
        290553653,
        1156863423,
        1237060221,
        1674612724,
        723452717,
        1555822107,
        1255441988,
        1044425306,
        1035587901,
        1287119770,
        761827446,
        1432926830,
        1361723162,
        1080846067,
        1120818681,
        1801614774,
        1535540516,
        2042117124,
        1576045014,
        1326785893,
        1474318539,
        2243969818,
        1226926355,
        1213360671,
        1178780333,
        1349960240,
        1768452342,
        959816376,
        900757567,
        2316793723,
        1643597461,
        1626936157,
        1966315855,
        1547396685,
        2290272144,
        1865987744,
        2547709618,
        2251079617,
        1539649042,
        2109471546,
        1442840603,
        2706395447,
        1911453253,
        1943961676,
        2296156229,
        2447991230,
        2432054390,
        2478086421,
        3117736795,
        2668830128,
        3420133681,
        3271100417,
        2388340435,
        3640158447,
        2573037644,
        3314963846,
        2595872232,
        3896012267,
        3493424914,
        3633565283,
        3166675994,
        3470271771,
        4967446268,
        3636396410,
        3602430179,
        3020621842,
        4071222256,
        4040429713,
        3340406038,
        3707624163,
        3841151405,
        4005957179,
        3235910682,
        3512804765,
        3758387102,
        3491871948,
        3363507696,
        4298923930,
        3266588666,
        3711851669,
        4167080269,
        5446883194,
        4081286334,
        4834066253,
        4451810677,
        4616705825,
        4165713626,
        5589826346,
        5028733221,
        5186301109,
        5604059195,
        4474266610,
        5706032707,
        5124189992,
        5545497322,
        6041919516,
        4859359335,
        4961476139,
        5169019976
      ],
      "customStats": {},
      "counters": {},
      "concurrency": 359,
      "pendingRequests": 30,
      "scenariosAvoided": 0
    },
    {
      "timestamp": "2020-06-28T22:38:12.683Z",
      "scenariosCreated": 0,
      "scenariosCompleted": 0,
      "requestsCompleted": 30,
      "latency": {
        "min": 5152.7,
        "max": 8083.6,
        "median": 6271.4,
        "p95": 7802.2,
        "p99": 8083.6
      },
      "rps": {
        "count": 0,
        "mean": null
      },
      "scenarioDuration": {
        "min": null,
        "max": null,
        "median": null,
        "p95": null,
        "p99": null
      },
      "scenarioCounts": {},
      "errors": {},
      "codes": {
        "200": 30
      },
      "matches": 0,
      "latencies": [
        5265529437,
        5152738663,
        5920472144,
        5646724875,
        6019577209,
        6382111299,
        5860838636,
        5827408958,
        5662274727,
        6352586473,
        5846193156,
        6048577326,
        6244278059,
        5927294075,
        5884166601,
        5876568172,
        6298503876,
        6416074249,
        6162264208,
        6317526207,
        7076638326,
        7059647660,
        6440662656,
        7285248039,
        6500929580,
        6515069154,
        7802233467,
        6690426965,
        8083590857,
        7568147369
      ],
      "customStats": {},
      "counters": {},
      "concurrency": 359,
      "pendingRequests": 0,
      "scenariosAvoided": 0
    },
    {
      "timestamp": "2020-06-28T22:38:22.685Z",
      "scenariosCreated": 0,
      "scenariosCompleted": 77,
      "requestsCompleted": 77,
      "latency": {
        "min": 65.5,
        "max": 755.5,
        "median": 291.2,
        "p95": 669.8,
        "p99": 744.7
      },
      "rps": {
        "count": 90,
        "mean": 18.67
      },
      "scenarioDuration": {
        "min": 30257.3,
        "max": 31271,
        "median": 30787.6,
        "p95": 31054,
        "p99": 31260.2
      },
      "scenarioCounts": {},
      "errors": {},
      "codes": {
        "200": 77
      },
      "matches": 0,
      "latencies": [
        112349407,
        147285136,
        97624754,
        70851093,
        342183401,
        115473050,
        199363899,
        305458639,
        120629516,
        107822139,
        299807616,
        192617337,
        183795305,
        256287367,
        143262960,
        74924799,
        259565583,
        229471572,
        365103614,
        388669432,
        289248521,
        523560864,
        389050026,
        330521052,
        208070740,
        291246477,
        306042222,
        401478062,
        487405159,
        715300437,
        431798313,
        678777342,
        755547239,
        713953872,
        646497778,
        398391387,
        398325646,
        399252476,
        399058768,
        271780472,
        105292491,
        114423706,
        116654496,
        72953254,
        86912041,
        99126579,
        65516803,
        67525983,
        69619974,
        97483579,
        97394722,
        356958107,
        364498251,
        361574391,
        358866965,
        360754190,
        363457980,
        277689819,
        270691568,
        272896670,
        272722197,
        118538187,
        118490917,
        119862484,
        129583523,
        193058005,
        367119938,
        396036350,
        454152936,
        547145802,
        579191855,
        590805999,
        605164285,
        652969963,
        597413188,
        653171439,
        653148089
      ],
      "customStats": {},
      "counters": {},
      "concurrency": 282,
      "pendingRequests": 13,
      "scenariosAvoided": 0
    },
    {
      "timestamp": "2020-06-28T22:38:32.688Z",
      "scenariosCreated": 85,
      "scenariosCompleted": 241,
      "requestsCompleted": 308,
      "latency": {
        "min": 64.6,
        "max": 1955.9,
        "median": 385,
        "p95": 797.7,
        "p99": 1017.3
      },
      "rps": {
        "count": 324,
        "mean": 32.79
      },
      "scenarioDuration": {
        "min": 30384.4,
        "max": 36353.5,
        "median": 31273.9,
        "p95": 34253.8,
        "p99": 35449.8
      },
      "scenarioCounts": {
        "Ride": 85
      },
      "errors": {},
      "codes": {
        "200": 308
      },
      "matches": 0,
      "latencies": [
        768128970,
        768279284,
        693602564,
        718695748,
        797034212,
        744639848,
        496944558,
        505728690,
        500325883,
        500286279,
        88130725,
        514955430,
        563045300,
        569918295,
        105168518,
        99731906,
        94289828,
        71984639,
        105236906,
        402435641,
        402554074,
        395787004,
        395635456,
        396641838,
        411205470,
        411331287,
        374163876,
        374939741,
        419863896,
        377436040,
        377433389,
        374134417,
        377340307,
        471938389,
        475216577,
        509861262,
        461884301,
        461922499,
        578822361,
        734257877,
        645664440,
        647586248,
        732532525,
        530820412,
        731500982,
        531340632,
        735301280,
        893808562,
        493514927,
        498528480,
        496665434,
        626195227,
        720367215,
        437826784,
        437887156,
        434479660,
        414779549,
        453651996,
        627086631,
        565306459,
        398365307,
        268557555,
        458742463,
        279423899,
        298578810,
        169928511,
        174497280,
        405383715,
        386161544,
        385999821,
        385864392,
        385483508,
        384953303,
        384607235,
        385024873,
        385047138,
        384895290,
        386447300,
        387528466,
        386215997,
        385150924,
        320927589,
        322352303,
        300113955,
        385293486,
        348152466,
        269105520,
        115646165,
        120737770,
        183121012,
        181129240,
        181164355,
        250462334,
        256459980,
        432110084,
        372794573,
        490929726,
        505303446,
        496639923,
        502754913,
        511656462,
        503103542,
        511312927,
        701390972,
        698395240,
        449081046,
        414342433,
        402737932,
        807747576,
        804003530,
        710821679,
        815749957,
        818412223,
        726464125,
        247051585,
        250815486,
        279267690,
        136685780,
        143423600,
        142296794,
        97574517,
        98234404,
        98061433,
        807841653,
        522466993,
        948971243,
        120539414,
        122579943,
        154529874,
        154584705,
        154258198,
        171662364,
        181803234,
        185543716,
        192362922,
        189371830,
        193760956,
        200212971,
        193930329,
        262502747,
        263070096,
        262957654,
        181557908,
        207366175,
        173688632,
        207602451,
        208126267,
        260445814,
        274155812,
        277963072,
        76273668,
        83425622,
        84705225,
        99387704,
        85481287,
        87191718,
        102306739,
        149895930,
        226675180,
        223556923,
        286688717,
        335623861,
        360226141,
        219670154,
        320673391,
        1111714746,
        179999789,
        64618052,
        113561609,
        81463127,
        402248878,
        403009484,
        403042183,
        402940667,
        408189704,
        309229625,
        400117845,
        400679594,
        400629404,
        341488816,
        321425034,
        153138660,
        116327658,
        163996352,
        162402930,
        82705791,
        309213443,
        88860590,
        493862778,
        182549027,
        150644808,
        142492039,
        612014526,
        215905023,
        316617485,
        517738621,
        184509254,
        157400400,
        169836931,
        338061073,
        99049215,
        105451968,
        105570568,
        134634518,
        301272216,
        425322247,
        280667713,
        258577590,
        363276990,
        199136099,
        150973385,
        84325726,
        452332324,
        133570946,
        130789112,
        130667924,
        336954759,
        166131461,
        704139932,
        319558470,
        137865194,
        404342984,
        75737014,
        82402276,
        95960532,
        302456249,
        381042114,
        415447120,
        313261967,
        104958041,
        99772940,
        228347581,
        385261334,
        407203087,
        487356706,
        190673415,
        259382491,
        327245245,
        584466429,
        344239500,
        776701261,
        490010089,
        278019214,
        407748748,
        123612490,
        102448117,
        102411501,
        166812248,
        363889403,
        591357855,
        286644826,
        392344253,
        392995729,
        315256510,
        721510375,
        393236468,
        384639192,
        924067163,
        389021822,
        625537586,
        457907613,
        526534377,
        257955279,
        293570027,
        638440091,
        515902363,
        445211285,
        457567203,
        292966540,
        349772633,
        483487610,
        1551248461,
        306421699,
        541864932,
        544175846,
        398658448,
        291878650,
        484851485,
        420571382,
        556065992,
        357343425,
        391989020,
        118274032,
        270487154,
        814081862,
        878918061,
        747437407,
        683405125,
        484402495,
        650916858,
        807260350,
        738268706,
        641621150,
        619700592,
        1955905804,
        778146944,
        456709270,
        462861077,
        569178914,
        514822212,
        426116576,
        546947523,
        552252744,
        897743838,
        535204654,
        435327029,
        466240308,
        560403351
      ],
      "customStats": {},
      "counters": {},
      "concurrency": 126,
      "pendingRequests": 29,
      "scenariosAvoided": 0
    },
    {
      "timestamp": "2020-06-28T22:38:42.689Z",
      "scenariosCreated": 24,
      "scenariosCompleted": 41,
      "requestsCompleted": 83,
      "latency": {
        "min": 113,
        "max": 1287.5,
        "median": 842.3,
        "p95": 1190.4,
        "p99": 1267.6
      },
      "rps": {
        "count": 54,
        "mean": 5.42
      },
      "scenarioDuration": {
        "min": 35544.8,
        "max": 38202.3,
        "median": 36695.9,
        "p95": 37850.4,
        "p99": 38202.3
      },
      "scenarioCounts": {
        "Ride": 24
      },
      "errors": {},
      "codes": {
        "200": 83
      },
      "matches": 0,
      "latencies": [
        926459740,
        950249452,
        719123964,
        1148650529,
        1149209966,
        1063165465,
        1186468341,
        1287521139,
        1086556604,
        1223387808,
        984999093,
        1057029892,
        825470232,
        923669598,
        788842881,
        856054600,
        1024768815,
        991311189,
        890611165,
        625636602,
        526829509,
        936747438,
        659354601,
        592939780,
        693636023,
        493933771,
        1016562082,
        670614261,
        639802018,
        606504328,
        566602377,
        1164302961,
        1164260287,
        688638486,
        628480804,
        1227218925,
        1197759539,
        842328511,
        1083125338,
        1081488371,
        958073544,
        976722833,
        820287724,
        1033262867,
        967397461,
        866745611,
        770242014,
        1005311747,
        838082769,
        805305366,
        743816033,
        612284492,
        804294372,
        981511279,
        804751793,
        955581948,
        908671213,
        976707703,
        844776188,
        945233658,
        1164367219,
        1034037391,
        801962834,
        1009400366,
        737560739,
        900137925,
        638477460,
        901822829,
        416749561,
        671455666,
        414975224,
        385068523,
        341832216,
        140653145,
        164090411,
        326510118,
        181314968,
        249548404,
        179475547,
        186056113,
        242247162,
        112968702,
        113017284
      ],
      "customStats": {},
      "counters": {},
      "concurrency": 109,
      "pendingRequests": 0,
      "scenariosAvoided": 0
    },
    {
      "timestamp": "2020-06-28T22:38:52.693Z",
      "scenariosCreated": 0,
      "scenariosCompleted": 0,
      "requestsCompleted": 0,
      "latency": {
        "min": null,
        "max": null,
        "median": null,
        "p95": null,
        "p99": null
      },
      "rps": {
        "count": 0,
        "mean": null
      },
      "scenarioDuration": {
        "min": null,
        "max": null,
        "median": null,
        "p95": null,
        "p99": null
      },
      "scenarioCounts": {},
      "errors": {},
      "codes": {},
      "matches": 0,
      "latencies": [],
      "customStats": {},
      "counters": {},
      "concurrency": 109,
      "pendingRequests": 0,
      "scenariosAvoided": 0
    },
    {
      "timestamp": "2020-06-28T22:39:02.695Z",
      "scenariosCreated": 0,
      "scenariosCompleted": 62,
      "requestsCompleted": 62,
      "latency": {
        "min": 64.6,
        "max": 900,
        "median": 294.5,
        "p95": 652.3,
        "p99": 880.5
      },
      "rps": {
        "count": 67,
        "mean": 15.16
      },
      "scenarioDuration": {
        "min": 30254,
        "max": 32214.4,
        "median": 30795.4,
        "p95": 31302.1,
        "p99": 32145.5
      },
      "scenarioCounts": {},
      "errors": {},
      "codes": {
        "200": 62
      },
      "matches": 0,
      "latencies": [
        299016673,
        78663118,
        86014172,
        234170888,
        231097548,
        228564384,
        184555813,
        181321819,
        64591738,
        68716950,
        230802151,
        239635369,
        119873268,
        119526980,
        119528322,
        401908101,
        256489454,
        126146365,
        78986100,
        79862233,
        85373557,
        228708231,
        201160290,
        259334197,
        266271747,
        383752255,
        403968053,
        233702164,
        259987523,
        124669317,
        394142600,
        394698224,
        323987040,
        396257447,
        394029301,
        395562664,
        396304371,
        316092021,
        529717993,
        157998273,
        199602969,
        199339786,
        899961127,
        737957964,
        633716155,
        651945163,
        652941814,
        550659493,
        556061703,
        609082570,
        112712349,
        392579308,
        387119797,
        388110084,
        387602135,
        369057021,
        356449467,
        387084454,
        407532033,
        407718397,
        367829820,
        289970629
      ],
      "customStats": {},
      "counters": {},
      "concurrency": 47,
      "pendingRequests": 5,
      "scenariosAvoided": 0
    },
    {
      "timestamp": "2020-06-28T22:39:12.695Z",
      "scenariosCreated": 133,
      "scenariosCompleted": 47,
      "requestsCompleted": 170,
      "latency": {
        "min": 72.2,
        "max": 1987.8,
        "median": 352.3,
        "p95": 1159.2,
        "p99": 1442.9
      },
      "rps": {
        "count": 175,
        "mean": 18
      },
      "scenarioDuration": {
        "min": 30793.6,
        "max": 32903.3,
        "median": 31274.5,
        "p95": 32301.3,
        "p99": 32903.3
      },
      "scenarioCounts": {
        "Ride": 133
      },
      "errors": {},
      "codes": {
        "200": 170
      },
      "matches": 0,
      "latencies": [
        313978762,
        421356639,
        439395690,
        345924085,
        386907135,
        141327381,
        72203246,
        408631207,
        408541094,
        392965754,
        393132519,
        393828438,
        392610140,
        392509486,
        394853383,
        392918735,
        394288498,
        394735060,
        393816484,
        426470441,
        180693776,
        523506196,
        529007893,
        528457703,
        530180970,
        529186795,
        152978848,
        309419021,
        97989862,
        657089580,
        663128592,
        641513247,
        549660838,
        928009485,
        399448860,
        308591798,
        299707341,
        552808626,
        315614324,
        386852363,
        393518597,
        247747985,
        137503218,
        309653481,
        810992205,
        375426609,
        280162327,
        196244686,
        1068569327,
        1019534087,
        1121122108,
        1152051953,
        1159178306,
        991873861,
        1251775137,
        1267646523,
        1002652019,
        1012401519,
        189917223,
        119630174,
        109708753,
        252139346,
        1193730726,
        1189662994,
        441510227,
        144603890,
        1987807958,
        1209282261,
        219600064,
        199163632,
        1479898268,
        102945315,
        1100722014,
        1001842147,
        325596048,
        694804839,
        1295150558,
        614606679,
        964770115,
        404564604,
        408996643,
        112148147,
        692398452,
        393670607,
        112532243,
        1049001645,
        580484810,
        116972086,
        372172875,
        474993978,
        149956685,
        440205825,
        141650585,
        180382502,
        149877524,
        112006812,
        109995100,
        301353573,
        351935944,
        398478913,
        368976938,
        221156861,
        346462289,
        297128911,
        176657452,
        232161297,
        124892132,
        189674934,
        191744537,
        142579875,
        154115109,
        215185479,
        163961894,
        122124978,
        118870556,
        117956584,
        186991311,
        120963894,
        349669076,
        300537363,
        305116704,
        336809732,
        588183794,
        487435605,
        388603631,
        539472246,
        264023444,
        332572165,
        301374998,
        222958333,
        791329894,
        196545188,
        304634470,
        96283922,
        236909468,
        187861922,
        129439780,
        107789243,
        344973005,
        295992931,
        395610218,
        455570134,
        184998371,
        412331715,
        363941474,
        336327774,
        623276208,
        375223023,
        785215626,
        262229487,
        615820705,
        682673168,
        345822052,
        248818185,
        200412294,
        128636912,
        221687235,
        123293017,
        300196893,
        450853997,
        401907586,
        352717574,
        318432325,
        537911729,
        490094419,
        390720795,
        344880127,
        294936296,
        194956578,
        201071324
      ],
      "customStats": {},
      "counters": {},
      "concurrency": 133,
      "pendingRequests": 10,
      "scenariosAvoided": 0
    },
    {
      "timestamp": "2020-06-28T22:39:22.698Z",
      "scenariosCreated": 26,
      "scenariosCompleted": 0,
      "requestsCompleted": 35,
      "latency": {
        "min": 116.7,
        "max": 891.1,
        "median": 371.6,
        "p95": 825.6,
        "p99": 891.1
      },
      "rps": {
        "count": 26,
        "mean": 2.61
      },
      "scenarioDuration": {
        "min": null,
        "max": null,
        "median": null,
        "p95": null,
        "p99": null
      },
      "scenarioCounts": {
        "Ride": 26
      },
      "errors": {},
      "codes": {
        "200": 35
      },
      "matches": 0,
      "latencies": [
        179251760,
        229973182,
        376684691,
        828048782,
        578794033,
        329009026,
        891134269,
        818067538,
        517726960,
        568598159,
        471253762,
        421542890,
        371626673,
        330041164,
        430366926,
        483168773,
        583804086,
        383089676,
        550674084,
        450415722,
        402081334,
        352780973,
        361257353,
        367806349,
        278412284,
        338052216,
        389088770,
        223218541,
        187450858,
        127147148,
        336432090,
        116688374,
        268768219,
        165273954,
        216914061
      ],
      "customStats": {},
      "counters": {},
      "concurrency": 159,
      "pendingRequests": 1,
      "scenariosAvoided": 0
    },
    {
      "timestamp": "2020-06-28T22:39:32.698Z",
      "scenariosCreated": 10,
      "scenariosCompleted": 0,
      "requestsCompleted": 11,
      "latency": {
        "min": 104,
        "max": 474.7,
        "median": 279.2,
        "p95": 469.3,
        "p99": 474.7
      },
      "rps": {
        "count": 10,
        "mean": 1.09
      },
      "scenarioDuration": {
        "min": null,
        "max": null,
        "median": null,
        "p95": null,
        "p99": null
      },
      "scenarioCounts": {
        "Ride": 10
      },
      "errors": {},
      "codes": {
        "200": 11
      },
      "matches": 0,
      "latencies": [
        207129531,
        281951009,
        279202002,
        352168245,
        474734697,
        270957473,
        317411139,
        365742646,
        150225891,
        138734957,
        103981834
      ],
      "customStats": {},
      "counters": {},
      "concurrency": 169,
      "pendingRequests": 0,
      "scenariosAvoided": 0
    },
    {
      "timestamp": "2020-06-28T22:39:42.701Z",
      "scenariosCreated": 10,
      "scenariosCompleted": 121,
      "requestsCompleted": 130,
      "latency": {
        "min": 59.9,
        "max": 705.3,
        "median": 188.4,
        "p95": 580.8,
        "p99": 679.5
      },
      "rps": {
        "count": 133,
        "mean": 14.49
      },
      "scenarioDuration": {
        "min": 30185.4,
        "max": 31780.5,
        "median": 30556.2,
        "p95": 31217.2,
        "p99": 31701.6
      },
      "scenarioCounts": {
        "Ride": 10
      },
      "errors": {},
      "codes": {
        "200": 130
      },
      "matches": 0,
      "latencies": [
        150579502,
        356740972,
        354470110,
        106071775,
        98868668,
        167936051,
        396134275,
        228637145,
        397123699,
        92731264,
        104899220,
        315575470,
        207167727,
        112593137,
        113630749,
        155566078,
        69603650,
        115105686,
        65483173,
        59870613,
        101388534,
        371490768,
        280574840,
        248233701,
        173765053,
        583453832,
        146911123,
        184483162,
        193683037,
        72095602,
        101018818,
        99706462,
        195511648,
        251377175,
        99289438,
        310452902,
        577135626,
        189059158,
        90729172,
        307145786,
        222391036,
        222274307,
        88800150,
        447315469,
        149828231,
        244424048,
        379062908,
        167399113,
        201560483,
        423870667,
        116055316,
        705335013,
        579672181,
        672991891,
        338928150,
        344631601,
        84380949,
        95910942,
        252649438,
        232651384,
        231080245,
        268066190,
        295005085,
        80902050,
        102783965,
        426593743,
        79390231,
        91397456,
        201749093,
        570523978,
        599730078,
        580823249,
        201541477,
        151303502,
        641975373,
        656606161,
        487506208,
        103089264,
        440161782,
        144703682,
        299999325,
        159923063,
        167099603,
        164213901,
        172302906,
        197293310,
        160359296,
        92823718,
        106566962,
        279272953,
        148361243,
        143066612,
        157593249,
        201548036,
        255006625,
        249674654,
        160997748,
        118234218,
        143694163,
        69824329,
        79835333,
        80812983,
        268697226,
        135541395,
        124647796,
        90035374,
        202513474,
        187832444,
        134196451,
        104321599,
        176262160,
        197273394,
        195204276,
        164185920,
        256936926,
        233954136,
        308400194,
        406474889,
        321067710,
        322972889,
        100480921,
        106758419,
        126814093,
        135664898,
        230144131,
        177973339,
        312202341,
        143044716,
        194667834,
        312849707
      ],
      "customStats": {},
      "counters": {},
      "concurrency": 58,
      "pendingRequests": 3,
      "scenariosAvoided": 0
    },
    {
      "timestamp": "2020-06-28T22:39:52.701Z",
      "scenariosCreated": 1,
      "scenariosCompleted": 37,
      "requestsCompleted": 39,
      "latency": {
        "min": 61,
        "max": 636.2,
        "median": 268,
        "p95": 619.6,
        "p99": 636.2
      },
      "rps": {
        "count": 36,
        "mean": 3.62
      },
      "scenarioDuration": {
        "min": 30255.4,
        "max": 31227.1,
        "median": 30638.9,
        "p95": 31139.6,
        "p99": 31227.1
      },
      "scenarioCounts": {
        "Ride": 1
      },
      "errors": {},
      "codes": {
        "200": 39
      },
      "matches": 0,
      "latencies": [
        389929780,
        341272670,
        390963714,
        213357379,
        159275401,
        162241882,
        157723250,
        230688851,
        239392493,
        294369733,
        321914469,
        322588332,
        322495808,
        323129339,
        322189654,
        320907555,
        170084498,
        73251131,
        437312861,
        89727149,
        142404080,
        614339133,
        123938210,
        264493188,
        596473133,
        623869735,
        636190942,
        569907370,
        591407712,
        422170935,
        459137040,
        74952642,
        60963819,
        202061042,
        80405474,
        224514887,
        184935529,
        246258683,
        267972037
      ],
      "customStats": {},
      "counters": {},
      "concurrency": 22,
      "pendingRequests": 0,
      "scenariosAvoided": 0
    },
    {
      "timestamp": "2020-06-28T22:40:02.702Z",
      "scenariosCreated": 0,
      "scenariosCompleted": 10,
      "requestsCompleted": 10,
      "latency": {
        "min": 60.2,
        "max": 473.6,
        "median": 182.3,
        "p95": 473.6,
        "p99": 473.6
      },
      "rps": {
        "count": 11,
        "mean": 1.1
      },
      "scenarioDuration": {
        "min": 30228.5,
        "max": 30776.1,
        "median": 30487.2,
        "p95": 30776.1,
        "p99": 30776.1
      },
      "scenarioCounts": {},
      "errors": {},
      "codes": {
        "200": 10
      },
      "matches": 0,
      "latencies": [
        473621619,
        287902695,
        246301581,
        226005413,
        293982215,
        60220730,
        69417995,
        65317187,
        65915264,
        138592848
      ],
      "customStats": {},
      "counters": {},
      "concurrency": 12,
      "pendingRequests": 1,
      "scenariosAvoided": 0
    },
    {
      "timestamp": "2020-06-28T22:40:12.704Z",
      "scenariosCreated": 0,
      "scenariosCompleted": 10,
      "requestsCompleted": 10,
      "latency": {
        "min": 78.5,
        "max": 290.1,
        "median": 161.8,
        "p95": 290.1,
        "p99": 290.1
      },
      "rps": {
        "count": 9,
        "mean": 1
      },
      "scenarioDuration": {
        "min": 30202.8,
        "max": 30582.2,
        "median": 30393.4,
        "p95": 30582.2,
        "p99": 30582.2
      },
      "scenarioCounts": {},
      "errors": {},
      "codes": {
        "200": 10
      },
      "matches": 0,
      "latencies": [
        162113463,
        161477509,
        212647258,
        78531340,
        93893297,
        126167098,
        95422464,
        189079355,
        169565352,
        290144487
      ],
      "customStats": {},
      "counters": {},
      "concurrency": 2,
      "pendingRequests": 0,
      "scenariosAvoided": 0
    },
    {
      "timestamp": "2020-06-28T22:40:14.703Z",
      "scenariosCreated": 0,
      "scenariosCompleted": 2,
      "requestsCompleted": 2,
      "latency": {
        "min": 82.7,
        "max": 156.8,
        "median": 119.7,
        "p95": 156.8,
        "p99": 156.8
      },
      "rps": {
        "count": 2,
        "mean": 1.09
      },
      "scenarioDuration": {
        "min": 30506,
        "max": 30684.5,
        "median": 30595.3,
        "p95": 30684.5,
        "p99": 30684.5
      },
      "scenarioCounts": {},
      "errors": {},
      "codes": {
        "200": 2
      },
      "matches": 0,
      "latencies": [
        156755460,
        82717317
      ],
      "customStats": {},
      "counters": {},
      "concurrency": 0,
      "pendingRequests": 0,
      "scenariosAvoided": 0
    }
  ]
}